dbot-manager/__init__.py
dbot-manager/cli_user.py
dbot-manager/dbot-service.py
dbot-manager/microraiden/__init__.py
dbot-manager/microraiden/close_all_channels.py
dbot-manager/microraiden/config.py
dbot-manager/microraiden/constants.py
dbot-manager/microraiden/exceptions.py
dbot-manager/microraiden/header.py
dbot-manager/microraiden/make_helpers.py
dbot-manager/microraiden/channel_manager/__init__.py
dbot-manager/microraiden/channel_manager/blockchain.py
dbot-manager/microraiden/channel_manager/channel.py
dbot-manager/microraiden/channel_manager/manager.py
dbot-manager/microraiden/channel_manager/state.py
dbot-manager/microraiden/client/__init__.py
dbot-manager/microraiden/client/atn.py
dbot-manager/microraiden/client/channel.py
dbot-manager/microraiden/client/client.py
dbot-manager/microraiden/client/context.py
dbot-manager/microraiden/client/session.py
dbot-manager/microraiden/proxy/__init__.py
dbot-manager/microraiden/proxy/resources/__init__.py
dbot-manager/microraiden/proxy/resources/management.py
dbot-manager/microraiden/proxy/resources/request_data.py
dbot-manager/microraiden/utils/__init__.py
dbot-manager/microraiden/utils/contract.py
dbot-manager/microraiden/utils/crypto.py
dbot-manager/microraiden/utils/misc.py
dbot-manager/microraiden/utils/populus_compat.py
dbot-manager/microraiden/utils/private_key.py
dbot-manager/utils/__init__.py
dbot-manager/utils/account.py
dbot-manager/utils/contract.py
dbot-manager/utils/oss.py
dbot-manager/utils/swagger.py
dbot-manager/utils/tool.py
dbot_manager/__init__.py
dbot_manager/cli_user.py
dbot_manager/contracts.json
dbot_manager/dbot_service.py
dbot_manager/contracts/__init__.py
dbot_manager/microraiden/__init__.py
dbot_manager/microraiden/close_all_channels.py
dbot_manager/microraiden/config.py
dbot_manager/microraiden/constants.py
dbot_manager/microraiden/exceptions.py
dbot_manager/microraiden/header.py
dbot_manager/microraiden/make_helpers.py
dbot_manager-0.0.8.dist-info/METADATA
dbot_manager-0.0.8.dist-info/RECORD
dbot_manager-0.0.8.dist-info/WHEEL
dbot_manager-0.0.8.dist-info/top_level.txt
