Metadata-Version: 2.1
Name: dbot-manager
Version: 0.0.8
Summary: Develop tools for ATN DBot
Home-page: https://github.com/ATNIO/dbot-manager
Author: ovsoil
Author-email: huaxin.yu@atmatrix.org
License: UNKNOWN
Platform: UNKNOWN
Classifier: Programming Language :: Python :: 3
Classifier: License :: OSI Approved :: MIT License
Classifier: Operating System :: OS Independent
Requires-Dist: click (==6.7)
Requires-Dist: eth-utils (==1.2.2)
Requires-Dist: typing (==3.6.6)
Requires-Dist: eth-account (==0.3.0)
Requires-Dist: web3 (==4.7.2)
Requires-Dist: requests (==2.19.1)
